odoo/addons/brand/README.rst
odoo/addons/brand/__init__.py
odoo/addons/brand/__manifest__.py
odoo/addons/brand/i18n/brand.pot
odoo/addons/brand/i18n/de.po
odoo/addons/brand/i18n/pt_BR.po
odoo/addons/brand/models/__init__.py
odoo/addons/brand/models/res_brand.py
odoo/addons/brand/models/res_brand_mixin.py
odoo/addons/brand/models/res_company.py
odoo/addons/brand/models/res_config_settings.py
odoo/addons/brand/readme/CONTRIBUTORS.rst
odoo/addons/brand/readme/CREDITS.rst
odoo/addons/brand/readme/DESCRIPTION.rst
odoo/addons/brand/readme/USAGE.rst
odoo/addons/brand/security/res_brand.xml
odoo/addons/brand/static/description/icon.png
odoo/addons/brand/static/description/index.html
odoo/addons/brand/views/res_brand.xml
odoo/addons/brand/views/res_config_settings.xml
odoo12_addon_brand-12.0.1.1.3.dist-info/METADATA
odoo12_addon_brand-12.0.1.1.3.dist-info/WHEEL
odoo12_addon_brand-12.0.1.1.3.dist-info/top_level.txt
odoo12_addon_brand-12.0.1.1.3.dist-info/RECORD
