Metadata-Version: 2.1
Name: odoo12-addon-brand
Version: 12.0.1.1.3
Summary: This is a base addon for brand modules. It adds the brand object and its menu and define an abstract model to be inherited from branded objects
Home-page: https://github.com/OCA/brand
Author: Odoo Community Association (OCA),ACSONE SA/NV
Author-email: support@odoo-community.org
License: LGPL-3
Platform: UNKNOWN
Classifier: Programming Language :: Python
Classifier: Framework :: Odoo
Classifier: Framework :: Odoo :: 12.0
Classifier: License :: OSI Approved :: GNU Lesser General Public License v3 (LGPLv3)
Requires-Python: >=3.5
Requires-Dist: odoo (<12.1dev,>=12.0a)
